clubhouse/__init__.py
clubhouse/__init__.pyc
clubhouse/admin/__init__.py
clubhouse/contrib/__init__.py
clubhouse/contrib/serializers.py
clubhouse/contrib/admin/__init__.py
clubhouse/contrib/admin/block.py
clubhouse/contrib/admin/page.py
clubhouse/contrib/migrations/0001_initial.py
clubhouse/contrib/migrations/0002_auto_20160225_1254.py
clubhouse/contrib/migrations/0003_auto_20160310_1651.py
clubhouse/contrib/migrations/0004_auto_20160310_1749.py
clubhouse/contrib/migrations/0005_auto_20160311_1302.py
clubhouse/contrib/migrations/0006_auto_20160323_1121.py
clubhouse/contrib/migrations/0007_auto_20160323_1134.py
clubhouse/contrib/migrations/0008_auto_20160323_1256.py
clubhouse/contrib/migrations/0009_auto_20160323_1724.py
clubhouse/contrib/migrations/0010_auto_20160330_0830.py
clubhouse/contrib/migrations/0011_galleryblock_zip_import.py
clubhouse/contrib/migrations/__init__.py
clubhouse/contrib/models/__init__.py
clubhouse/contrib/models/blocks.py
clubhouse/contrib/models/pages.py
clubhouse/contrib/models/types.py
clubhouse/contrib/templates/block-base.html
clubhouse/contrib/templates/aside-blocks/galleryblock.html
clubhouse/contrib/templates/aside-blocks/twitterfeedblock.html
clubhouse/contrib/templates/aside-blocks/verticalspacingblock.html
clubhouse/contrib/templates/content-blocks/formblock.html
clubhouse/contrib/templates/content-blocks/galleryblock.html
clubhouse/contrib/templates/content-blocks/groupingblock.html
clubhouse/contrib/templates/content-blocks/rowseparatorblock.html
clubhouse/contrib/templates/content-blocks/verticalspacingblock.html
clubhouse/contrib/templates/content-blocks/wysiwygblock.html
clubhouse/contrib/templates/pages/modularpage.html
clubhouse/core/__init__.py
clubhouse/core/fields.py
clubhouse/core/filters.py
clubhouse/core/options.py
clubhouse/core/serializers.py
clubhouse/core/settings.py
clubhouse/core/sites.py
clubhouse/core/widgets.py
clubhouse/core/models/__init__.py
django_clubhouse-0.2.19.dist-info/DESCRIPTION.rst
django_clubhouse-0.2.19.dist-info/METADATA
django_clubhouse-0.2.19.dist-info/RECORD
django_clubhouse-0.2.19.dist-info/WHEEL
django_clubhouse-0.2.19.dist-info/metadata.json
django_clubhouse-0.2.19.dist-info/top_level.txt
