Metadata-Version: 2.0
Name: django-clubhouse
Version: 0.2.19
Summary: An open source content management system build on the Django Framework, extending Mezzanine.
Home-page: https://github.com/chazmead/django-clubhouse
Author: Charles Mead
Author-email: chazmead89@gmail.com
License: BSD
Platform: UNKNOWN
Classifier: Development Status :: 3 - Alpha
Classifier: Intended Audience :: Developers
Classifier: Topic :: Software Development :: Build Tools
Classifier: License :: OSI Approved :: BSD License
Classifier: Operating System :: OS Independent
Classifier: Programming Language :: Python
Classifier: Programming Language :: Python :: 2.7
Classifier: Topic :: Internet :: WWW/HTTP
Classifier: Topic :: Internet :: WWW/HTTP :: Dynamic Content
Classifier: Topic :: Internet :: WWW/HTTP :: WSGI
Classifier: Topic :: Software Development :: Libraries :: Application Frameworks
Classifier: Topic :: Software Development :: Libraries :: Python Modules
Requires-Dist: Mezzanine (==4.1.0)
Requires-Dist: django-image-cropping (==1.0.3)
Requires-Dist: easy-thumbnails (==2.3)
Requires-Dist: filebrowser-safe (==0.4.3)
Requires-Dist: grappelli-safe (==0.4.2)
